pigai/__init__.py
pigai-1.16.dist-info/LICENSE
pigai-1.16.dist-info/METADATA
pigai-1.16.dist-info/WHEEL
pigai-1.16.dist-info/dependency_links.txt
pigai-1.16.dist-info/top_level.txt
pigai-1.16.dist-info/RECORD
